arrow_field/__init__.py
arrow_field/form_fields.py
arrow_field/model_fields.py
arrow_field/models.py
django_arrow_field-0.1.1.dist-info/DESCRIPTION.rst
django_arrow_field-0.1.1.dist-info/METADATA
django_arrow_field-0.1.1.dist-info/pydist.json
django_arrow_field-0.1.1.dist-info/RECORD
django_arrow_field-0.1.1.dist-info/top_level.txt
django_arrow_field-0.1.1.dist-info/WHEEL
