Metadata-Version: 2.0
Name: django-arrow-field
Version: 0.1.1
Summary: Django arrow datetime field
Home-page: https://github.com/gizmag/django-arrow-field
Author: Gizmag
Author-email: tech@gizmag.com
License: UNKNOWN
Platform: UNKNOWN
Requires-Dist: django
Requires-Dist: arrow
